sksurgerytorch/__init__.py
sksurgerytorch/_version.py
sksurgerytorch/models/__init__.py
sksurgerytorch/models/high_res_stereo.py
sksurgerytorch/models/high_res_stereo_model.py
sksurgerytorch/models/volume_to_surface.py
sksurgerytorch/models/volume_to_surface_model.py
sksurgerytorch/ui/__init__.py
sksurgerytorch/ui/sksurgerytorch_hsmnet_command_line.py
scikit_surgerytorch-0.2.6.dist-info/LICENSE
scikit_surgerytorch-0.2.6.dist-info/METADATA
scikit_surgerytorch-0.2.6.dist-info/WHEEL
scikit_surgerytorch-0.2.6.dist-info/entry_points.txt
scikit_surgerytorch-0.2.6.dist-info/top_level.txt
scikit_surgerytorch-0.2.6.dist-info/RECORD
