Metadata-Version: 2.1
Name: scikit-surgerytorch
Version: 0.2.6
Summary: scikit-surgerytorch is a Python package
Home-page: https://github.com/UCL/scikit-surgerytorch
Author: Thomas Dowrick
Author-email: t.dowrick@ucl.ac.uk
License: BSD-3 license
Keywords: medical imaging
Platform: UNKNOWN
Classifier: Development Status :: 3 - Alpha
Classifier: Intended Audience :: Developers
Classifier: Intended Audience :: Healthcare Industry
Classifier: Intended Audience :: Information Technology
Classifier: Intended Audience :: Science/Research
Classifier: License :: OSI Approved :: BSD License
Classifier: Programming Language :: Python
Classifier: Programming Language :: Python :: 2
Classifier: Programming Language :: Python :: 3
Classifier: Topic :: Scientific/Engineering :: Information Analysis
Classifier: Topic :: Scientific/Engineering :: Medical Science Apps.
Requires-Dist: six (>=1.10)
Requires-Dist: numpy (>=1.11)
Requires-Dist: torch
Requires-Dist: torchvision
Requires-Dist: opencv-contrib-python-headless (>=4.2.0.32)
